setup.cfg
setup.py
regroup/__init__.py
regroup/cluster.py
regroup/relax.py
regroup/tokenizer.py
regroup.egg-info/PKG-INFO
regroup.egg-info/SOURCES.txt
regroup.egg-info/dependency_links.txt
regroup.egg-info/top_level.txt