Metadata-Version: 1.0
Name: regroup
Version: 0.1
Summary: generate regular expresions describing input strings
Home-page: https://github.com/rflynn/regroup
Author: Ryan Flynn
Author-email: parseerror+github@gmail.com
License: MIT
Keywords: regex,regular expression,strings,summarize,text,generator,induction,DAWG,automata,clustering,lcsp
Platform: UNKNOWN
